Metadata-Version: 2.1
Name: qsr
Version: 2.6.5
Summary: the simple screen record
Home-page: UNKNOWN
Author: R-Stu-Softdev
Author-email: r.studio.animation@gmail.com
License: UNKNOWN
Keywords: python,video,record,screen recorder,screen,rstuteam,simpleqsr
Platform: UNKNOWN
Classifier: Programming Language :: Python :: 3
Classifier: Operating System :: Unix
Classifier: Operating System :: MacOS :: MacOS X
Classifier: Operating System :: Microsoft :: Windows
License-File: LICENSE
